otlp_stdout_span_exporter/__init__.py
otlp_stdout_span_exporter/constants.py
otlp_stdout_span_exporter/exporter.py
otlp_stdout_span_exporter/py.typed
otlp_stdout_span_exporter/version.py
otlp_stdout_span_exporter-0.16.0.dist-info/METADATA
otlp_stdout_span_exporter-0.16.0.dist-info/WHEEL
otlp_stdout_span_exporter-0.16.0.dist-info/entry_points.txt
otlp_stdout_span_exporter-0.16.0.dist-info/RECORD
