Metadata-Version: 2.4
Name: otlp-stdout-span-exporter
Version: 0.16.0
Summary: OpenTelemetry span exporter that writes to stdout in OTLP format
Project-URL: homepage, https://github.com/dev7a/serverless-otlp-forwarder/
Project-URL: repository, https://github.com/dev7a/serverless-otlp-forwarder/tree/main/packages/python/otlp-stdout-span-exporter
Author-email: Alessandro Bologna <alessandro.bologna@gmail.com>
License: MIT
Keywords: exporter,opentelemetry,otlp,spans,stdout,tracing
Classifier: Development Status :: 4 - Beta
Classifier: Intended Audience :: Developers
Classifier: License :: OSI Approved :: MIT License
Classifier: Programming Language :: Python :: 3.12
Classifier: Topic :: Software Development :: Libraries :: Python Modules
Classifier: Topic :: System :: Monitoring
Requires-Python: >=3.12
Requires-Dist: opentelemetry-exporter-otlp-proto-common>=1.30.0
Requires-Dist: opentelemetry-sdk>=1.30.0
Provides-Extra: dev
Requires-Dist: mypy>=1.15.0; extra == 'dev'
Requires-Dist: pytest-asyncio>=1.0.0; extra == 'dev'
Requires-Dist: pytest-cov>=6.2.1; extra == 'dev'
Requires-Dist: pytest>=8.4.0; extra == 'dev'
Requires-Dist: ruff>=0.9.6; extra == 'dev'
